[
  {
    "type": { "type": { "tid": "float" } },
    "expr": { "Literal": { "value": { "Number": 1.5 } } }
  },
  {
    "type": { "type": { "tid": "float" } },
    "expr": { "Literal": { "value": { "Number": 1.5 } } }
  },
  {
    "type": {
      "variable": { "name": "T", "ref": { "type": { "tid": "number" } } }
    },
    "expr": {
      "Binary": {
        "left": { "Literal": { "value": { "Number": 1.5 } } },
        "op": { "type": { "PLUS": {} }, "lexeme": "+", "line": 1 },
        "right": { "Literal": { "value": { "Number": 1.5 } } }
      }
    }
  }
]
